[
    {
        "id": 1,
        "title": "Сайт ветролётиков и гоночек",
        "skills": "1 HTML, CSS, JS",
        "photo": "slider-1.jpg",
        "link": "//google.com",
        "desc": "Изучал что-то очень быстро без должной практики"
    },
    {
        "id": 2,
        "title": "Сайт джум джум",
        "skills": "2 HTML, CSS, JS",
        "photo": "slider-2.jpg",
        "link": "//google.com",
        "desc": "Делал ctrlc ctrl v"
    },
    {
        "id": 3,
        "title": "Сайт образования катионов",
        "skills": "3 HTML, CSS, JS",
        "photo": "slider-3.jpg",
        "link": "//google.com",
        "desc": "В результате имеем то, что имеем"
    },
    {
        "id": 3,
        "title": "Сайт образования катионов",
        "skills": "3 HTML, CSS, JS",
        "photo": "slider-3.jpg",
        "link": "//google.com",
        "desc": "В результате имеем то, что имеем"
    }

]